modelo_risco/__init__.py
modelo_risco/_nbdev.py
modelo_risco/modelo_risco_coletivo.py
modelo_risco/modelo_risco_individual.py
modelo_risco-0.0.4.dist-info/LICENSE
modelo_risco-0.0.4.dist-info/METADATA
modelo_risco-0.0.4.dist-info/WHEEL
modelo_risco-0.0.4.dist-info/entry_points.txt
modelo_risco-0.0.4.dist-info/top_level.txt
modelo_risco-0.0.4.dist-info/RECORD
