Metadata-Version: 2.1
Name: modelo-risco
Version: 0.0.4
Summary: Desenvolvimento do Modelo de Risco Atuarial individual e coletivo.
Home-page: https://github.com/filipeclduarte/modelo_risco/tree/master/
Author: Filipe C. L. Duarte
Author-email: filipe_pb_duarte@hotmail.com
License: Apache Software License 2.0
Keywords: risco_atuarial
Platform: UNKNOWN
Classifier: Development Status :: 3 - Alpha
Classifier: Intended Audience :: Developers
Classifier: License :: OSI Approved :: Apache Software License
Classifier: Natural Language :: English
Classifier: Programming Language :: Python :: 3.6
Classifier: Programming Language :: Python :: 3.7
Classifier: Programming Language :: Python :: 3.8
Requires-Python: >=3.6
